uncertain_panda/__init__.py
uncertain_panda/plotting/__init__.py
uncertain_panda/plotting/helpers.py
uncertain_panda/uncertainties/__init__.py
uncertain_panda/uncertainties/bootstrap_result.py
uncertain_panda/uncertainties/calculation.py
uncertain_panda/uncertainties/calculators.py
uncertain_panda/uncertainties/functions.py
uncertain_panda/utils/__init__.py
uncertain_panda/utils/numerics.py
uncertain_panda/utils/pandas_utils.py
uncertain_panda-0.3.0.dist-info/LICENSE
uncertain_panda-0.3.0.dist-info/WHEEL
uncertain_panda-0.3.0.dist-info/METADATA
uncertain_panda-0.3.0.dist-info/RECORD
