Metadata-Version: 2.1
Name: uncertain_panda
Version: 0.3.0
Summary: Pandas with uncertainties
Home-page: https://github.com/nils-braun/uncertain_panda
License: UNKNOWN
Author: Nils Braun
Author-email: nils.braun@kit.edu
Classifier: License :: OSI Approved :: GNU General Public License v3 or later (GPLv3+)
Requires-Dist: pandas>=0.23.4
Requires-Dist: uncertainties
Requires-Dist: matplotlib
Provides-Extra: .none
